sparseSpACE/BasisFunctions.py
sparseSpACE/ComponentGridInfo.py
sparseSpACE/DEMachineLearning.py
sparseSpACE/DimAdaptiveCombi.py
sparseSpACE/ErrorCalculator.py
sparseSpACE/Extrapolation.py
sparseSpACE/Function.py
sparseSpACE/Grid.py
sparseSpACE/GridOperation.py
sparseSpACE/Hierarchization.py
sparseSpACE/Integrator.py
sparseSpACE/MonteCarlo.py
sparseSpACE/PerformTestCase.py
sparseSpACE/RefinementContainer.py
sparseSpACE/RefinementObject.py
sparseSpACE/StandardCombi.py
sparseSpACE/Utils.py
sparseSpACE/__init__.py
sparseSpACE/combiScheme.py
sparseSpACE/spatiallyAdaptiveBase.py
sparseSpACE/spatiallyAdaptiveCell.py
sparseSpACE/spatiallyAdaptiveExtendSplit.py
sparseSpACE/spatiallyAdaptiveSingleDimension2.py
sparseSpACE-1.1.0.dist-info/LICENSE
sparseSpACE-1.1.0.dist-info/METADATA
sparseSpACE-1.1.0.dist-info/WHEEL
sparseSpACE-1.1.0.dist-info/top_level.txt
sparseSpACE-1.1.0.dist-info/RECORD
