Metadata-Version: 2.1
Name: sparseSpACE
Version: 1.1.0
Summary: sparseSpACE - the Sparse Grid Spatially Adaptive Combination Environment implements different variants of the spatially adaptive combination technique
Home-page: https://github.com/obersteiner/sparseSpACE
Author: Michael Obersteiner
Author-email: michael.obersteiner@mytum.de
License: LGPL-3.0
Platform: UNKNOWN
Classifier: Programming Language :: Python :: 3
Classifier: Programming Language :: Python :: 3.5
License-File: LICENSE
Requires-Dist: numpy
Requires-Dist: scipy
Requires-Dist: matplotlib
Requires-Dist: dill
Requires-Dist: scikit-learn
Requires-Dist: chaospy
Requires-Dist: sympy
